psr/__init__.py
psr/collection.py
psr/config.py
psr/expression.py
psr/expression_builder.py
psr/func_unit.py
psr/logging.py
psr/metrics.py
psr/psr.py
psr/typing.py
psr/utils.py
psr/base/__init__.py
psr/base/base.py
psr/base/exception.py
psr/base/formatter.py
psr/base/func_unit.py
psr/base/tree.py
parametric_sr-0.1.0.dist-info/METADATA
parametric_sr-0.1.0.dist-info/WHEEL
parametric_sr-0.1.0.dist-info/top_level.txt
parametric_sr-0.1.0.dist-info/RECORD
