Metadata-Version: 2.4
Name: parametric-sr
Version: 0.1.0
Summary: Parametric Symbolic Regression for Modeling a Series of Datasets via Genetic Programming
Author: Sijie Fu
License-Expression: Apache-2.0
Project-URL: Homepage, https://github.com/SijieFu/parametric-symbolic-regression
Project-URL: Repository, https://github.com/SijieFu/parametric-symbolic-regression.git
Project-URL: Issues, https://github.com/SijieFu/parametric-symbolic-regression/issues
Project-URL: Changelog, https://github.com/SijieFu/parametric-symbolic-regression/blob/main/CHANGELOG.md
Keywords: symbolic regression,genetic programming,parametric symbolic regression,mathematical pattern discovery,machine learning,artificial intelligence
Classifier: Development Status :: 3 - Alpha
Classifier: Intended Audience :: Science/Research
Classifier: Operating System :: OS Independent
Classifier: Programming Language :: Python :: 3
Classifier: Programming Language :: Python :: 3.12
Classifier: Programming Language :: Python :: 3.13
Classifier: Topic :: Scientific/Engineering :: Artificial Intelligence
Classifier: Topic :: Scientific/Engineering :: Mathematics
Classifier: Typing :: Typed
Requires-Python: >=3.12
Requires-Dist: numpy>=2.3
Requires-Dist: scipy>=1.16
Requires-Dist: sympy>=1.14
Requires-Dist: matplotlib>=3.10
Requires-Dist: networkx>=3.5
Requires-Dist: scikit-learn>=1.7
Provides-Extra: all
Requires-Dist: scipy-stubs>=1.16; extra == "all"
Requires-Dist: pygraphviz>=1.14; extra == "all"
Provides-Extra: dev
Requires-Dist: mypy>=1.17; extra == "dev"
Requires-Dist: pre-commit>=4.2; extra == "dev"
Requires-Dist: pre-commit-hooks>=6.0; extra == "dev"
Requires-Dist: pytest>=8.4; extra == "dev"
Requires-Dist: sphinx>=8.2; extra == "dev"
Requires-Dist: sphinx-autodoc-typehints>=3.2; extra == "dev"
Requires-Dist: sphinx_rtd_theme>=3.0; extra == "dev"
Requires-Dist: numpydoc>=1.9; extra == "dev"
